sqlmorph/__init__.py
sqlmorph/cli.py
sqlmorph/core.py
sqlmorph/db_shell.py
sqlmorph/diagram_generator.py
sqlmorph/doctorr.py
sqlmorph/explainer.py
sqlmorph/help_text.py
sqlmorph/inspector.py
sqlmorph/migrator.py
sqlmorph/model_generator.py
sqlmorph/planner.py
sqlmorph/seeder.py
sqlmorph/tracker.py
sqlmorph/utils.py
sqlmorph/watcher.py
sqlmorph-1.0.0.dist-info/METADATA
sqlmorph-1.0.0.dist-info/WHEEL
sqlmorph-1.0.0.dist-info/entry_points.txt
sqlmorph-1.0.0.dist-info/RECORD
