Metadata-Version: 2.4
Name: sqlmorph
Version: 1.0.0
Summary: The missing migration layer for SQLModel. Zero-config, auto-detecting schema migrations.
License: MIT
Keywords: sqlmodel,migration,sqlalchemy,orm,database,fastapi
Author: pyomerhrr@gmail.com
Requires-Python: >=3.9,<4.0
Classifier: License :: OSI Approved :: MIT License
Classifier: Programming Language :: Python :: 3
Classifier: Programming Language :: Python :: 3.9
Classifier: Programming Language :: Python :: 3.10
Classifier: Programming Language :: Python :: 3.11
Classifier: Programming Language :: Python :: 3.12
Classifier: Programming Language :: Python :: 3.13
Classifier: Programming Language :: Python :: 3.14
Requires-Dist: sqlmodel (>=0.0.16,<0.0.17)
Requires-Dist: typer[all] (>=0.12.3,<0.13.0)
Requires-Dist: watchdog (>=4.0.0,<5.0.0)
Project-URL: Homepage, https://github.com/omehrrr/sqlmorph
Project-URL: Repository, https://github.com/omehrrr/sqlmorph
